Metadata-Version: 1.0
Name: noobElectric
Version: 0.5
Summary: Tools for Electrical Engineering
Home-page: https://github.com/nicholasericksen/noobElectric
Author: nicholasericksen
Author-email: ericksennicholas@gmail.com
License: MIT
Platform: UNKNOWN
